jinja2sql/__init__.py
jinja2sql/_core.py
jinja2sql/py.typed
jinja2sql-0.8.0.dist-info/METADATA
jinja2sql-0.8.0.dist-info/WHEEL
jinja2sql-0.8.0.dist-info/licenses/LICENSE
jinja2sql-0.8.0.dist-info/RECORD
