Metadata-Version: 2.4
Name: jinja2sql
Version: 0.8.0
Summary: Jinja Templates to SQL
Project-URL: Repository, https://github.com/antonrh/jinja2sql
Author-email: Anton Ruhlov <antonruhlov@gmail.com>
License-Expression: MIT
License-File: LICENSE
Keywords: database,db,jinja,queries,query,sql,template
Classifier: Development Status :: 5 - Production/Stable
Classifier: Intended Audience :: Developers
Classifier: Intended Audience :: Information Technology
Classifier: Intended Audience :: System Administrators
Classifier: License :: OSI Approved :: MIT License
Classifier: Operating System :: OS Independent
Classifier: Programming Language :: Python :: 3
Classifier: Programming Language :: Python :: 3 :: Only
Classifier: Programming Language :: Python :: 3.9
Classifier: Programming Language :: Python :: 3.10
Classifier: Programming Language :: Python :: 3.11
Classifier: Programming Language :: Python :: 3.12
Classifier: Programming Language :: Python :: 3.13
Classifier: Topic :: Software Development
Classifier: Topic :: Software Development :: Libraries
Classifier: Topic :: Software Development :: Libraries :: Python Modules
Classifier: Typing :: Typed
Requires-Python: ~=3.9
Requires-Dist: jinja2<4,>=3.1.2
Requires-Dist: typing-extensions<5,>=4.12.2
